allure/__init__.py
allure/adaptor.py
allure/common.py
allure/constants.py
allure/pytest_plugin.py
allure/rules.py
allure/structure.py
allure/utils.py
allure_adaptor_nio-0.4.dist-info/LICENSE
allure_adaptor_nio-0.4.dist-info/METADATA
allure_adaptor_nio-0.4.dist-info/WHEEL
allure_adaptor_nio-0.4.dist-info/entry_points.txt
allure_adaptor_nio-0.4.dist-info/top_level.txt
allure_adaptor_nio-0.4.dist-info/RECORD
