Metadata-Version: 1.0
Name: allure-adaptor-nio
Version: 0.4
Summary: change get_marker to get_closest_marker
Home-page: UNKNOWN
Author: UNKNOWN
Author-email: UNKNOWN
License: UNKNOWN
Platform: UNKNOWN
